{"__symbolic":"module","version":4,"metadata":{"BrowserService":{"__symbolic":"class","members":{}},"CookieService":{"__symbolic":"class","members":{"get":[{"__symbolic":"method"}],"set":[{"__symbolic":"method"}]}},"IAreaData":{"__symbolic":"interface"},"SplitComponent":{"__symbolic":"class","decorators":[{"__symbolic":"call","expression":{"__symbolic":"reference","module":"@angular/core","name":"Component","line":25,"character":1},"arguments":[{"selector":"split","changeDetection":{"__symbolic":"select","expression":{"__symbolic":"reference","module":"@angular/core","name":"ChangeDetectionStrategy","line":27,"character":21},"member":"OnPush"},"styles":["\n        :host {\n            display: flex;\n            flex-wrap: nowrap;\n            justify-content: flex-start;\n            flex-direction: row;\n        }\n\n        :host.vertical {\n            flex-direction: column;\n        }\n\n        split-gutter {\n            flex-grow: 0;\n            flex-shrink: 0;\n            flex-basis: 10px;\n            height: 100%;\n            background-color: #eeeeee;\n            background-position: 50%;\n            background-repeat: no-repeat;\n        }\n\n        :host.vertical split-gutter {\n            width: 100%;\n        }\n\n        :host /deep/ split-area {\n            transition: flex-basis 0.3s;\n        }  \n\n        :host.notrans /deep/ split-area {\n            transition: none !important;\n        }      \n\n        :host /deep/ split-area.notshow {\n            flex-basis: 0 !important;\n            overflow: hidden !important;\n        }      \n\n        :host.vertical /deep/ split-area.notshow {\n            max-width: 0;\n            flex-basis: 0 !important;\n            overflow: hidden !important;\n        }\n    "],"template":"\n        <div #cover style=\"position:absolute;left:0;top:0;right:0;bottom:0;z-index:100;\"\n            [style.display]=\"coverDisplay | async\"></div>\n        <ng-content></ng-content>\n        <ng-template ngFor let-area [ngForOf]=\"areas\" let-index=\"index\" let-last=\"last\">\n            <split-gutter *ngIf=\"last === false && area.component.visible && !isLastVisibleArea(area)\" \n                          [order]=\"index*2+1\"\n                          [direction]=\"direction\"\n                          [size]=\"gutterSize\"\n                          [disabled]=\"disabled\"\n                          (mousedown)=\"startDragging($event, index*2+1)\"\n                          (touchstart)=\"startDragging($event, index*2+1)\"></split-gutter>\n        </ng-template>"}]}],"members":{"direction":[{"__symbolic":"property","decorators":[{"__symbolic":"call","expression":{"__symbolic":"reference","module":"@angular/core","name":"Input","line":88,"character":5}}]}],"width":[{"__symbolic":"property","decorators":[{"__symbolic":"call","expression":{"__symbolic":"reference","module":"@angular/core","name":"Input","line":89,"character":5}}]}],"height":[{"__symbolic":"property","decorators":[{"__symbolic":"call","expression":{"__symbolic":"reference","module":"@angular/core","name":"Input","line":90,"character":5}}]}],"gutterSize":[{"__symbolic":"property","decorators":[{"__symbolic":"call","expression":{"__symbolic":"reference","module":"@angular/core","name":"Input","line":91,"character":5}}]}],"disabled":[{"__symbolic":"property","decorators":[{"__symbolic":"call","expression":{"__symbolic":"reference","module":"@angular/core","name":"Input","line":92,"character":5}}]}],"animateAreaToggle":[{"__symbolic":"property","decorators":[{"__symbolic":"call","expression":{"__symbolic":"reference","module":"@angular/core","name":"Input","line":93,"character":5}}]}],"dragStart":[{"__symbolic":"property","decorators":[{"__symbolic":"call","expression":{"__symbolic":"reference","module":"@angular/core","name":"Output","line":95,"character":5}}]}],"dragProgress":[{"__symbolic":"property","decorators":[{"__symbolic":"call","expression":{"__symbolic":"reference","module":"@angular/core","name":"Output","line":96,"character":5}}]}],"dragEnd":[{"__symbolic":"property","decorators":[{"__symbolic":"call","expression":{"__symbolic":"reference","module":"@angular/core","name":"Output","line":97,"character":5}}]}],"saveStates":[{"__symbolic":"property","decorators":[{"__symbolic":"call","expression":{"__symbolic":"reference","module":"@angular/core","name":"Input","line":99,"character":5}}]}],"name":[{"__symbolic":"property","decorators":[{"__symbolic":"call","expression":{"__symbolic":"reference","module":"@angular/core","name":"Input","line":101,"character":5}}]}],"visibleTransitionEnd":[{"__symbolic":"property","decorators":[{"__symbolic":"call","expression":{"__symbolic":"reference","module":"@angular/core","name":"Output","line":119,"character":5}}]}],"styleFlexDirection":[{"__symbolic":"property","decorators":[{"__symbolic":"call","expression":{"__symbolic":"reference","module":"@angular/core","name":"HostBinding","line":121,"character":5},"arguments":["class.vertical"]}]}],"dragging":[{"__symbolic":"property","decorators":[{"__symbolic":"call","expression":{"__symbolic":"reference","module":"@angular/core","name":"HostBinding","line":125,"character":5},"arguments":["class.notrans"]}]}],"styleWidth":[{"__symbolic":"property","decorators":[{"__symbolic":"call","expression":{"__symbolic":"reference","module":"@angular/core","name":"HostBinding","line":130,"character":5},"arguments":["style.width"]}]}],"styleHeight":[{"__symbolic":"property","decorators":[{"__symbolic":"call","expression":{"__symbolic":"reference","module":"@angular/core","name":"HostBinding","line":134,"character":5},"arguments":["style.height"]}]}],"__ctor__":[{"__symbolic":"constructor","parameters":[{"__symbolic":"reference","name":"SplitStateService"},{"__symbolic":"reference","module":"@angular/core","name":"ChangeDetectorRef","line":156,"character":23},{"__symbolic":"reference","module":"@angular/core","name":"ElementRef","line":157,"character":28},{"__symbolic":"reference","module":"@angular/core","name":"Renderer2","line":158,"character":26}]}],"ngOnChanges":[{"__symbolic":"method"}],"ngAfterViewInit":[{"__symbolic":"method"}],"addArea":[{"__symbolic":"method"}],"updateArea":[{"__symbolic":"method"}],"removeArea":[{"__symbolic":"method"}],"hideArea":[{"__symbolic":"method"}],"showArea":[{"__symbolic":"method"}],"isLastVisibleArea":[{"__symbolic":"method"}],"refresh":[{"__symbolic":"method"}],"refreshStyleSizes":[{"__symbolic":"method"}],"startDragging":[{"__symbolic":"method"}],"dragEvent":[{"__symbolic":"method"}],"drag":[{"__symbolic":"method"}],"stopDragging":[{"__symbolic":"method"}],"_saveState":[{"__symbolic":"method"}],"notify":[{"__symbolic":"method"}],"ngOnDestroy":[{"__symbolic":"method"}]}},"SplitAreaDirective":{"__symbolic":"class","decorators":[{"__symbolic":"call","expression":{"__symbolic":"reference","module":"@angular/core","name":"Directive","line":7,"character":1},"arguments":[{"selector":"split-area","host":{"[style.flex-grow]":"\"0\"","[style.flex-shrink]":"\"0\"","[style.overflow-x]":"\"hidden\"","[style.overflow-y]":"\"auto\"","[style.height]":"\"100%\"","[class.notshow]":"!visible","(transitionend)":"onSizingTransitionEnd($event)","$quoted$":["[style.flex-grow]","[style.flex-shrink]","[style.overflow-x]","[style.overflow-y]","[style.height]","[class.notshow]","(transitionend)"]}}]}],"members":{"order":[{"__symbolic":"property","decorators":[{"__symbolic":"call","expression":{"__symbolic":"reference","module":"@angular/core","name":"Input","line":22,"character":5}}]}],"size":[{"__symbolic":"property","decorators":[{"__symbolic":"call","expression":{"__symbolic":"reference","module":"@angular/core","name":"Input","line":28,"character":5}}]}],"minSizePixel":[{"__symbolic":"property","decorators":[{"__symbolic":"call","expression":{"__symbolic":"reference","module":"@angular/core","name":"Input","line":34,"character":5}}]}],"visible":[{"__symbolic":"property","decorators":[{"__symbolic":"call","expression":{"__symbolic":"reference","module":"@angular/core","name":"Input","line":40,"character":5}}]}],"__ctor__":[{"__symbolic":"constructor","parameters":[{"__symbolic":"reference","module":"@angular/core","name":"ElementRef","line":58,"character":36},{"__symbolic":"reference","module":"@angular/core","name":"Renderer2","line":59,"character":26},{"__symbolic":"reference","name":"SplitComponent"}]}],"ngOnInit":[{"__symbolic":"method"}],"lockEvents":[{"__symbolic":"method"}],"unlockEvents":[{"__symbolic":"method"}],"setStyle":[{"__symbolic":"method"}],"ngOnDestroy":[{"__symbolic":"method"}],"onSizingTransitionEnd":[{"__symbolic":"method"}]}},"SplitGutterDirective":{"__symbolic":"class","decorators":[{"__symbolic":"call","expression":{"__symbolic":"reference","module":"@angular/core","name":"Directive","line":2,"character":1},"arguments":[{"selector":"split-gutter"}]}],"members":{"order":[{"__symbolic":"property","decorators":[{"__symbolic":"call","expression":{"__symbolic":"reference","module":"@angular/core","name":"Input","line":7,"character":5}}]}],"direction":[{"__symbolic":"property","decorators":[{"__symbolic":"call","expression":{"__symbolic":"reference","module":"@angular/core","name":"Input","line":12,"character":5}}]}],"size":[{"__symbolic":"property","decorators":[{"__symbolic":"call","expression":{"__symbolic":"reference","module":"@angular/core","name":"Input","line":17,"character":5}}]}],"disabled":[{"__symbolic":"property","decorators":[{"__symbolic":"call","expression":{"__symbolic":"reference","module":"@angular/core","name":"Input","line":22,"character":5}}]}],"__ctor__":[{"__symbolic":"constructor","parameters":[{"__symbolic":"reference","module":"@angular/core","name":"ElementRef","line":27,"character":36},{"__symbolic":"reference","module":"@angular/core","name":"Renderer2","line":28,"character":34}]}],"refreshStyle":[{"__symbolic":"method"}],"setStyle":[{"__symbolic":"method"}],"getCursor":[{"__symbolic":"method"}],"getImage":[{"__symbolic":"method"}]}},"SplitAreaState":{"__symbolic":"class","members":{}},"SplitStateService":{"__symbolic":"class","decorators":[{"__symbolic":"call","expression":{"__symbolic":"reference","module":"@angular/core","name":"Injectable","line":8,"character":1}}],"members":{"__ctor__":[{"__symbolic":"constructor","parameters":[{"__symbolic":"reference","name":"CookieService"}]}],"saveState":[{"__symbolic":"method"}],"loadState":[{"__symbolic":"method"}]}},"AngularSplitModule":{"__symbolic":"class","decorators":[{"__symbolic":"call","expression":{"__symbolic":"reference","module":"@angular/core","name":"NgModule","line":9,"character":1},"arguments":[{"imports":[{"__symbolic":"reference","module":"@angular/common","name":"CommonModule","line":11,"character":8}],"declarations":[{"__symbolic":"reference","name":"SplitComponent"},{"__symbolic":"reference","name":"SplitAreaDirective"},{"__symbolic":"reference","name":"SplitGutterDirective"}],"exports":[{"__symbolic":"reference","name":"SplitComponent"},{"__symbolic":"reference","name":"SplitAreaDirective"},{"__symbolic":"reference","name":"SplitGutterDirective"}],"providers":[{"__symbolic":"reference","name":"SplitStateService"},{"__symbolic":"reference","name":"CookieService"}]}]}],"members":{}}},"origins":{"BrowserService":"./browserService","CookieService":"./cookieService","IAreaData":"./split.component","SplitComponent":"./split.component","SplitAreaDirective":"./splitArea.directive","SplitGutterDirective":"./splitGutter.directive","SplitAreaState":"./splitStateService","SplitStateService":"./splitStateService","AngularSplitModule":"./angularSplit.module"},"importAs":"angular-split"}